FactorBacktesterModel/__init__.py
FactorBacktesterModel/extractdata.py
FactorBacktesterModel/Factors/__init__.py
Model/__init__.py
Model/extractdata.py
Model/Factors/__init__.py
FactorBacktesterModel-0.0.1.dist-info/METADATA
FactorBacktesterModel-0.0.1.dist-info/WHEEL
FactorBacktesterModel-0.0.1.dist-info/top_level.txt
FactorBacktesterModel-0.0.1.dist-info/RECORD
