Metadata-Version: 2.1
Name: FactorBacktesterModel
Version: 0.0.1
Summary: Factor - Backtester
Home-page: UNKNOWN
Author: Akshit Kwatra
Author-email: <akshit@truebeacon.com>
License: UNKNOWN
Keywords: python,first package
Platform: UNKNOWN
Classifier: Development Status :: 3 - Alpha
Classifier: Intended Audience :: Education
Classifier: Programming Language :: Python :: 2
Classifier: Programming Language :: Python :: 3
Classifier: Operating System :: MacOS :: MacOS X
Classifier: Operating System :: Microsoft :: Windows
